{
  "$schema": "https://developer.microsoft.com/json-schemas/spfx-build/package-solution.schema.json",
  "solution": {
    "name": "security-client-side-solution",
    "id": "1b26033b-f594-4d2b-b7d3-703fa25e3bdc",
    "version": "1.0.0.0",
    "includeClientSideAssets": true,
    "skipFeatureDeployment": true,
    "isDomainIsolated": false,
    "developer": {
      "name": "",
      "websiteUrl": "",
      "privacyUrl": "",
      "termsOfUseUrl": "",
      "mpnId": "Undefined-1.20.0"
    },
    "metadata": {
      "shortDescription": {
        "default": "security description"
      },
      "longDescription": {
        "default": "security description"
      },
      "screenshotPaths": [],
      "videoUrl": "",
      "categories": []
    },
    "features": [
      {
        "title": "security Feature",
        "description": "The feature that activates elements of the security solution.",
        "id": "e16fd1ce-4aa2-48ac-a299-fcc310b54abd",
        "version": "1.0.0.0"
      }
    ]
  },
  "paths": {
    "zippedPackage": "solution/security.sppkg"
  }
}
